README.rst
setup.py
data/trinucleotide_demo.pdf
data/trinucleotide_demo.png
data/trinucleotide_demo.txt
ngsfig/__init__.py
ngsfig.egg-info/PKG-INFO
ngsfig.egg-info/SOURCES.txt
ngsfig.egg-info/__init__.py
ngsfig.egg-info/dependency_links.txt
ngsfig.egg-info/requires.txt
ngsfig.egg-info/top_level.txt
ngsfig/graphics/__init__.py
ngsfig/graphics/trinucleotide.py
ngsfig/utils/__init__.py
ngsfig/utils/dna.py