Metadata-Version: 1.0
Name: ngsfig
Version: 0.1.1
Summary: Classes and functions for NGS data illustration
Home-page: https://github.com/xiaobeizhao/ngsfigpy
Author: Xiaobei Zhao
Author-email: xiaobei_zhao(at)med.unc.edu
License: GNU LGPL
Platform: UNKNOWN
